aiotaskq/__init__.py
aiotaskq/__main__.py
aiotaskq/app.py
aiotaskq/concurrency_manager.py
aiotaskq/config.py
aiotaskq/constants.py
aiotaskq/exceptions.py
aiotaskq/interfaces.py
aiotaskq/pubsub.py
aiotaskq/serde.py
aiotaskq/task.py
aiotaskq/utils.py
aiotaskq/worker.py
aiotaskq-0.0.17.dist-info/licenses/LICENSE
aiotaskq-0.0.17.dist-info/METADATA
aiotaskq-0.0.17.dist-info/WHEEL
aiotaskq-0.0.17.dist-info/entry_points.txt
aiotaskq-0.0.17.dist-info/top_level.txt
aiotaskq-0.0.17.dist-info/RECORD
