Metadata-Version: 2.4
Name: aiotaskq
Version: 0.0.17
Summary: A simple asynchronous task queue
Author-email: Imran Ariffin <ariffin.imran@gmail.com>
License: Copyright (c) 2018 The Python Packaging Authority
Project-URL: Bug Tracker, https://github.com/imranariffin/aiotaskq/issues
Classifier: Programming Language :: Python :: 3
Classifier: License :: OSI Approved :: MIT License
Classifier: Operating System :: OS Independent
Requires-Python: >=3.10
License-File: LICENSE
Requires-Dist: aioredis<2.1.0,>=2.0.0
Requires-Dist: jsonpickle<3.1.0,>=3.0.0
Requires-Dist: tomlkit<0.12.0,>=0.11.0
Requires-Dist: typer<0.5.0,>=0.4.0
Provides-Extra: dev
Requires-Dist: black<23.0.0,>=22.2.0; extra == "dev"
Requires-Dist: celery<5.5.0,>=5.4.0; extra == "dev"
Requires-Dist: coverage<6.5.0,>=6.4.0; extra == "dev"
Requires-Dist: django-stubs<5.2.0,>=5.1.0; extra == "dev"
Requires-Dist: mypy<1.0,>=0.931; extra == "dev"
Requires-Dist: mypy-extensions<0.5.0,>=0.4.0; extra == "dev"
Requires-Dist: pytest-asyncio<0.20.0,>=0.19.0; extra == "dev"
Requires-Dist: pylint<2.15.0,>=2.14.0; extra == "dev"
Requires-Dist: psycopg2<2.10.0,>=2.9.0; extra == "dev"
Requires-Dist: pytest<7.2.0,>=7.1.0; extra == "dev"
Requires-Dist: redis<5.3.0,>=5.2.0; extra == "dev"
Requires-Dist: typing_extensions<4.12.0,>=4.11.0; extra == "dev"
Dynamic: license-file
